linchemin/__init__.py
linchemin/utilities.py
linchemin/IO/__init__.py
linchemin/IO/io.py
linchemin/cgu/__init__.py
linchemin/cgu/convert.py
linchemin/cgu/discgraph.py
linchemin/cgu/iron.py
linchemin/cgu/route_enumeration.py
linchemin/cgu/route_mining.py
linchemin/cgu/route_sanity_check.py
linchemin/cgu/syngraph.py
linchemin/cgu/syngraph_operations.py
linchemin/cgu/translate.py
linchemin/cgu/graph_transformations/__init__.py
linchemin/cgu/graph_transformations/data_model_converters.py
linchemin/cgu/graph_transformations/exceptions.py
linchemin/cgu/graph_transformations/format_translators.py
linchemin/cgu/graph_transformations/supporting_functions.py
linchemin/cheminfo/__init__.py
linchemin/cheminfo/atom_mapping.py
linchemin/cheminfo/chemical_hashes.py
linchemin/cheminfo/chemical_similarity.py
linchemin/cheminfo/constructors.py
linchemin/cheminfo/depiction.py
linchemin/cheminfo/functions.py
linchemin/cheminfo/models.py
linchemin/cheminfo/model_constructors/__init__.py
linchemin/cheminfo/model_constructors/disconnection_constructor.py
linchemin/cheminfo/model_constructors/legacy_constructors.py
linchemin/cheminfo/model_constructors/ratam_constructor.py
linchemin/configuration/__init__.py
linchemin/configuration/config.py
linchemin/configuration/defaults.py
linchemin/interfaces/__init__.py
linchemin/interfaces/cli.py
linchemin/interfaces/facade.py
linchemin/interfaces/utils_interfaces.py
linchemin/interfaces/workflows.py
linchemin/interfaces/writers.py
linchemin/rem/__init__.py
linchemin/rem/clustering.py
linchemin/rem/graph_distance.py
linchemin/rem/node_descriptors.py
linchemin/rem/route_descriptors.py
linchemin/rem/route_metrics.py
linchemin/rem/route_scoring.py
linchemin/rem/step_descriptors.py
linchemin/rem/rem_utils/__init__.py
linchemin/rem/rem_utils/classification_schema.py
linchemin/rem/rem_utils/distance_strategy.py
linchemin/services/callbacks.py
linchemin/services/decorators.py
linchemin/services/general.py
linchemin/services/response_handler.py
linchemin-3.2.0.dist-info/licenses/LICENSE
linchemin-3.2.0.dist-info/METADATA
linchemin-3.2.0.dist-info/WHEEL
linchemin-3.2.0.dist-info/entry_points.txt
linchemin-3.2.0.dist-info/top_level.txt
linchemin-3.2.0.dist-info/RECORD
