Metadata-Version: 2.4
Name: linchemin
Version: 3.2.0
Summary: Toolkit to create, manipulate, and query networks of Chemical Reactions and Chemicals
Author-email: Marco Stenta <marco.stenta@syngenta.com>, Marta Pasquini <marta.pasquini@syngenta.com>
License: MIT License
Project-URL: homepage, https://linchemin.github.io
Project-URL: repository, https://github.com/syngenta/linchemin
Keywords: reaction,chemoinformatics,computer-aided synthesis planning
Classifier: Intended Audience :: Science/Research
Classifier: License :: OSI Approved :: MIT License
Classifier: Operating System :: MacOS :: MacOS X
Classifier: Operating System :: Microsoft :: Windows
Classifier: Operating System :: OS Independent
Classifier: Operating System :: POSIX :: Linux
Classifier: Programming Language :: Python
Classifier: Programming Language :: Python :: 3
Classifier: Programming Language :: Python :: 3 :: Only
Classifier: Programming Language :: Python :: 3.8
Classifier: Programming Language :: Python :: 3.9
Classifier: Programming Language :: Python :: 3.10
Classifier: Programming Language :: Python :: 3.11
Classifier: Programming Language :: Python :: Implementation :: CPython
Classifier: Topic :: Scientific/Engineering :: Chemistry
Requires-Python: >=3.8
License-File: LICENSE
Requires-Dist: dynaconf
Requires-Dist: hdbscan>=0.8.29
Requires-Dist: joblib
Requires-Dist: networkx
Requires-Dist: numpy
Requires-Dist: pandas
Requires-Dist: pydantic
Requires-Dist: pydot
Requires-Dist: pyyaml
Requires-Dist: requests
Requires-Dist: rdchiral
Requires-Dist: rdkit>=2023.9
Requires-Dist: scikit-learn
Provides-Extra: dev
Requires-Dist: bumpver; extra == "dev"
Requires-Dist: flake8==6.0.0; extra == "dev"
Requires-Dist: isort==5.12.0; extra == "dev"
Requires-Dist: black==23.9.1; extra == "dev"
Requires-Dist: pre-commit==3.2.*; extra == "dev"
Requires-Dist: pytest-cov; extra == "dev"
Requires-Dist: pytest; extra == "dev"
Requires-Dist: sphinx; extra == "dev"
Requires-Dist: pytest-mock; extra == "dev"
Dynamic: license-file
